{
  "actionmappings": [
    {
      "messagebodyclass": "class ch.ethz.inf.vs.a4.minker.einz.messageparsing.messagetypes.EinzRegisterSuccessMessageBody",
      "mapstoaction": "class ch.ethz.inf.vs.a4.minker.einz.messageparsing.actiontypes.EinzRegisterSuccessAction"
    },
	{
	  "messagebodyclass": "class ch.ethz.inf.vs.a4.minker.einz.messageparsing.messagetypes.EinzRegisterFailureMessageBody",
	  "mapstoaction": "class ch.ethz.inf.vs.a4.minker.einz.messageparsing.actiontypes.EinzRegisterFailureAction"
	},
	{
	  "messagebodyclass": "class ch.ethz.inf.vs.a4.minker.einz.messageparsing.messagetypes.EinzUpdateLobbyListMessageBody",
	  "mapstoaction": "class ch.ethz.inf.vs.a4.minker.einz.messageparsing.actiontypes.EinzUpdateLobbyListAction"
	},
	{
	  "messagebodyclass": "class ch.ethz.inf.vs.a4.minker.einz.messageparsing.messagetypes.EinzUnregisterResponseMessageBody",
	  "mapstoaction": "class ch.ethz.inf.vs.a4.minker.einz.messageparsing.actiontypes.EinzUnregisterResponseAction"
	},
	{
	  "messagebodyclass": "class ch.ethz.inf.vs.a4.minker.einz.messageparsing.messagetypes.EinzKeepaliveMessageBody",
	  "mapstoaction": "class ch.ethz.inf.vs.a4.minker.einz.messageparsing.actiontypes.EinzKeepaliveAction"
	}
  ]
}